snipsmanagercore/__init__.py
snipsmanagercore/audio_player.py
snipsmanagercore/instant_time.py
snipsmanagercore/intent_parser.py
snipsmanagercore/leds_service.py
snipsmanagercore/pretty_printer.py
snipsmanagercore/server.py
snipsmanagercore/singleton.py
snipsmanagercore/snips_dialogue_api.py
snipsmanagercore/sound_service.py
snipsmanagercore/state_handler.py
snipsmanagercore/thread_handler.py
snipsmanagercore/time_interval.py
snipsmanagercore/tts.py
snipsmanagercore/usb_utils.py
snipsmanagercore/data/sounds/music_marimba_error_chord_2x.wav
snipsmanagercore/data/sounds/pad_glow_power_off.wav
snipsmanagercore/data/sounds/pad_glow_welcome1.wav
snipsmanagercore/data/sounds/pad_soft_off.wav
snipsmanagercore/data/sounds/pad_soft_on.wav
snipsmanagercore-0.1.7.0.0.dist-info/DESCRIPTION.rst
snipsmanagercore-0.1.7.0.0.dist-info/METADATA
snipsmanagercore-0.1.7.0.0.dist-info/RECORD
snipsmanagercore-0.1.7.0.0.dist-info/WHEEL
snipsmanagercore-0.1.7.0.0.dist-info/metadata.json
snipsmanagercore-0.1.7.0.0.dist-info/top_level.txt
