Metadata-Version: 2.0
Name: snipsmanagercore
Version: 0.1.7.0.0
Summary: The Snips manager core utilities for creating end-to-end assistants
Home-page: https://github.com/snipsco/snipsmanagercore
Author: Snips
Author-email: labs@snips.ai
License: MIT
Keywords: snips
Platform: UNKNOWN
Requires-Dist: cython (==0.21.1)
Requires-Dist: gTTS (==1.2.2)
Requires-Dist: hidapi (==0.7.99.post20)
Requires-Dist: paho-mqtt (==1.3.0)
Requires-Dist: pyaudio (==0.2.8)
Requires-Dist: pygame (==1.9.3)
Requires-Dist: pyusb (==1.0.0)
Requires-Dist: pyyaml (==3.12)
Requires-Dist: snips-respeaker (==0.6.2)
Requires-Dist: webrtcvad (==2.0.10)
